django_mptt_nomagic-0.2.3.dist-info/DESCRIPTION.rst
django_mptt_nomagic-0.2.3.dist-info/METADATA
django_mptt_nomagic-0.2.3.dist-info/RECORD
django_mptt_nomagic-0.2.3.dist-info/WHEEL
django_mptt_nomagic-0.2.3.dist-info/metadata.json
django_mptt_nomagic-0.2.3.dist-info/top_level.txt
mptt/__init__.py
mptt/admin.py
mptt/exceptions.py
mptt/fields.py
mptt/forms.py
mptt/managers.py
mptt/models.py
mptt/querysets.py
mptt/settings.py
mptt/signals.py
mptt/utils.py
mptt/locale/de/LC_MESSAGES/django.mo
mptt/locale/de/LC_MESSAGES/django.po
mptt/locale/dk/LC_MESSAGES/django.mo
mptt/locale/dk/LC_MESSAGES/django.po
mptt/locale/es/LC_MESSAGES/django.mo
mptt/locale/es/LC_MESSAGES/django.po
mptt/locale/es_AR/LC_MESSAGES/django.mo
mptt/locale/es_AR/LC_MESSAGES/django.po
mptt/locale/fr/LC_MESSAGES/django.mo
mptt/locale/fr/LC_MESSAGES/django.po
mptt/locale/mn/LC_MESSAGES/django.mo
mptt/locale/mn/LC_MESSAGES/django.po
mptt/locale/nb/LC_MESSAGES/django.mo
mptt/locale/nb/LC_MESSAGES/django.po
mptt/locale/pl/LC_MESSAGES/django.mo
mptt/locale/pl/LC_MESSAGES/django.po
mptt/locale/pt_BR/LC_MESSAGES/django.mo
mptt/locale/pt_BR/LC_MESSAGES/django.po
mptt/locale/ru/LC_MESSAGES/django.mo
mptt/locale/ru/LC_MESSAGES/django.po
mptt/static/mptt/arrow-move.png
mptt/static/mptt/disclosure-down.png
mptt/static/mptt/disclosure-right.png
mptt/static/mptt/draggable-admin.css
mptt/static/mptt/draggable-admin.js
mptt/templates/admin/grappelli_mptt_change_list.html
mptt/templates/admin/grappelli_mptt_change_list_results.html
mptt/templates/admin/mptt_change_list.html
mptt/templates/admin/mptt_change_list_results.html
mptt/templates/admin/mptt_filter.html
mptt/templatetags/__init__.py
mptt/templatetags/mptt_admin.py
mptt/templatetags/mptt_tags.py
