Metadata-Version: 2.0
Name: django-mptt-nomagic
Version: 0.2.3
Summary: Utilities for implementing Modified Preorder Tree Traversal
Home-page: https://github.com/matthiask/django-mptt/tree/mk/nomagic
Author: Matthias Kestenholz
Author-email: mk@feinheit.ch
License: MIT License
Platform: UNKNOWN
Classifier: Development Status :: 4 - Beta
Classifier: Environment :: Web Environment
Classifier: Framework :: Django
Classifier: Intended Audience :: Developers
Classifier: License :: OSI Approved :: MIT License
Classifier: Operating System :: OS Independent
Classifier: Programming Language :: Python
Classifier: Programming Language :: Python :: 2
Classifier: Programming Language :: Python :: 2.7
Classifier: Programming Language :: Python :: 3
Classifier: Programming Language :: Python :: 3.4
Classifier: Programming Language :: Python :: 3.5
Classifier: Topic :: Utilities
